optomo/__init__.py
optomo/_version.py
optomo-0.0.1.dist-info/METADATA
optomo-0.0.1.dist-info/WHEEL
optomo-0.0.1.dist-info/top_level.txt
optomo-0.0.1.dist-info/RECORD
